LICENSE.txt
README.md
setup.cfg
setup.py
scale_smartcapture.egg-info/PKG-INFO
scale_smartcapture.egg-info/SOURCES.txt
scale_smartcapture.egg-info/dependency_links.txt
scale_smartcapture.egg-info/requires.txt
scale_smartcapture.egg-info/top_level.txt
smartcapture/__init__.py
smartcapture/client.py
smartcapture/constants.py
smartcapture/logger.py
smartcapture/scql.py
smartcapture/trigger.py
smartcapture/utils.py
test/test_scql.py