Metadata-Version: 2.1
Name: scale-smartcapture
Version: 0.5
Summary: The official Python client library for Smart Capture
Home-page: https://github.com/scaleapi/smart-capture-sdk
Download-URL: https://github.com/scaleapi/smart-capture-sdk/archive/refs/tags/v0.5.tar.gz
Author: Scale AI Smartcapture Team
License: MIT
Keywords: smartcapture,scale
License-File: LICENSE.txt
